easy_rag/__init__.py
easy_rag/document.py
easy_rag/framework.py
easy_rag/session.py
easy_rag/embeddings/__init__.py
easy_rag/embeddings/base.py
easy_rag/embeddings/huggingface_embeddings.py
easy_rag/embeddings/openai_embeddings.py
easy_rag/llms/__init__.py
easy_rag/llms/base.py
easy_rag/llms/gemini.py
easy_rag/llms/openai.py
easy_rag/retrievers/__init__.py
easy_rag/retrievers/base.py
easy_rag/retrievers/similarity.py
easy_rag/utils/__init__.py
easy_rag/utils/text_splitter.py
easy_rag/vectorstores/__init__.py
easy_rag/vectorstores/base.py
easy_rag/vectorstores/chroma.py
easy_rag/vectorstores/faiss.py
rag_easy-0.1.1.dist-info/METADATA
rag_easy-0.1.1.dist-info/WHEEL
rag_easy-0.1.1.dist-info/top_level.txt
rag_easy-0.1.1.dist-info/RECORD
