Metadata-Version: 2.1
Name: rag-easy
Version: 0.1.1
Summary: A simple and secure RAG framework to rag any LLM model with ease.
Home-page: https://github.com/Tarun0951/easy-rag
Author: Tarun Baswa
Author-email: tarunbaswa9059@gmail.com
Classifier: Intended Audience :: Developers
Classifier: License :: OSI Approved :: MIT License
Classifier: Operating System :: OS Independent
Classifier: Programming Language :: Python :: 3
Classifier: Programming Language :: Python :: 3.7
Classifier: Programming Language :: Python :: 3.8
Classifier: Programming Language :: Python :: 3.9
Classifier: Programming Language :: Python :: 3.10
Requires-Dist: openai >=0.28.0
Requires-Dist: chromadb >=0.3.0
Requires-Dist: faiss-cpu >=1.7.0
Requires-Dist: google-generativeai
Requires-Dist: transformers >=4.0.0
Requires-Dist: torch >=1.0.0
Provides-Extra: dev
Requires-Dist: pytest >=6.0 ; extra == 'dev'
Requires-Dist: black ; extra == 'dev'
Requires-Dist: isort ; extra == 'dev'
Requires-Dist: flake8 ; extra == 'dev'
